retriv/__init__.py
retriv/base_retriever.py
retriv/hybrid_retriever.py
retriv/paths.py
retriv/autotune/__init__.py
retriv/autotune/bm25_autotune.py
retriv/autotune/merger_autotune.py
retriv/dense_retriever/__init__.py
retriv/dense_retriever/ann_searcher.py
retriv/dense_retriever/dense_retriever.py
retriv/dense_retriever/encoder.py
retriv/experimental/__init__.py
retriv/experimental/advanced_retriever.py
retriv/merger/__init__.py
retriv/merger/merger.py
retriv/merger/normalization.py
retriv/sparse_retriever/__init__.py
retriv/sparse_retriever/build_inverted_index.py
retriv/sparse_retriever/sparse_retriever.py
retriv/sparse_retriever/preprocessing/__init__.py
retriv/sparse_retriever/preprocessing/normalization.py
retriv/sparse_retriever/preprocessing/stemmer.py
retriv/sparse_retriever/preprocessing/stopwords.py
retriv/sparse_retriever/preprocessing/tokenizer.py
retriv/sparse_retriever/preprocessing/utils.py
retriv/sparse_retriever/sparse_retrieval_models/__init__.py
retriv/sparse_retriever/sparse_retrieval_models/bm25.py
retriv/sparse_retriever/sparse_retrieval_models/tf_idf.py
retriv/utils/__init__.py
retriv/utils/numba_utils.py
retriv-0.2.3.dist-info/LICENSE
retriv-0.2.3.dist-info/METADATA
retriv-0.2.3.dist-info/WHEEL
retriv-0.2.3.dist-info/top_level.txt
retriv-0.2.3.dist-info/RECORD
