Metadata-Version: 2.1
Name: retriv
Version: 0.2.3
Summary: retriv: A Python Search Engine for Humans.
Home-page: https://github.com/AmenRa/retriv
Author: Elias Bassani
Author-email: elias.bssn@gmail.com
License: UNKNOWN
Keywords: information retrieval,search engine,bm25,numba,sparse retrieval,dense retrieval,hybrid retrieval,neural information retrieval
Platform: UNKNOWN
Classifier: Programming Language :: Python :: 3
Classifier: License :: OSI Approved :: MIT License
Classifier: Intended Audience :: Science/Research
Classifier: Operating System :: OS Independent
Classifier: Topic :: Text Processing :: General
Requires-Python: >=3.8
License-File: LICENSE
Requires-Dist: numpy
Requires-Dist: nltk
Requires-Dist: numba >=0.54.1
Requires-Dist: tqdm
Requires-Dist: optuna
Requires-Dist: krovetzstemmer
Requires-Dist: pystemmer ==2.0.1
Requires-Dist: unidecode
Requires-Dist: scikit-learn
Requires-Dist: ranx
Requires-Dist: indxr
Requires-Dist: oneliner-utils
Requires-Dist: torch
Requires-Dist: torchvision
Requires-Dist: torchaudio
Requires-Dist: transformers[torch]
Requires-Dist: faiss-cpu
Requires-Dist: autofaiss
Requires-Dist: multipipe
